{
  "Satyam Kumar": {
    "april2021": {
      "day01": {
        "total": 526,
        "horoscope/vedic": 111,
        "prediction/dailysun": 71,
        "matching/ashtakoot": 131,
        "horoscope/chartimage": 212,
        "matching/papasamya": 111
      },
      "day02": {
        "total": 526,
        "horoscope/vedic": 12,
        "horoscope/chartimage": 212,
        "prediction/dailysun": 71,
        "matching/ashtakoot": 56,
        "matching/papasamya": 59
      },
      "day03": {
        "total": 524,
        "horoscope/vedic": 33,
        "horoscope/chartimage": 12,
        "prediction/dailysun": 71,
        "matching/ashtakoot": 555,
        "matching/papasamya": 12
      },
      "day04": {
        "total": 526,
        "horoscope/vedic": 111,
        "horoscope/chartimage": 212,
        "prediction/dailysun": 71,
        "matching/ashtakoot": 111,
        "matching/papasamya": 111
      },
      "day05": {
        "total": 526,
        "horoscope/vedic": 12,
        "horoscope/chartimage": 212,
        "prediction/dailysun": 71,
        "matching/ashtakoot": 56,
        "matching/papasamya": 59
      },
      "day06": {
        "total": 643,
        "horoscope/vedic": 33,
        "horoscope/chartimage": 12,
        "prediction/dailysun": 71,
        "matching/ashtakoot": 555,
        "matching/papasamya": 12
      },
      "day07": {
        "total": 526,
        "horoscope/vedic": 111,
        "horoscope/chartimage": 212,
        "prediction/dailysun": 71,
        "matching/ashtakoot": 111,
        "matching/papasamya": 111
      },
      "day08": {
        "total": 526,
        "horoscope/vedic": 12,
        "horoscope/chartimage": 212,
        "prediction/dailysun": 71,
        "matching/ashtakoot": 56,
        "matching/papasamya": 59
      },
      "day09": {
        "total": 590,
        "horoscope/vedic": 33,
        "horoscope/chartimage": 12,
        "prediction/dailysun": 71,
        "matching/ashtakoot": 555,
        "matching/papasamya": 12
      },
      "day10": {
        "total": 526,
        "horoscope/vedic": 111,
        "horoscope/chartimage": 212,
        "prediction/dailysun": 71,
        "matching/ashtakoot": 111,
        "matching/papasamya": 111
      },
      "day11": {
        "total": 526,
        "horoscope/vedic": 12,
        "horoscope/chartimage": 212,
        "prediction/dailysun": 71,
        "matching/ashtakoot": 56,
        "matching/papasamya": 59
      },
      "day12": {
        "total": 643,
        "horoscope/vedic": 33,
        "horoscope/chartimage": 12,
        "prediction/dailysun": 71,
        "matching/ashtakoot": 555,
        "matching/papasamya": 12
      },
      "day13": {
        "total": 526,
        "horoscope/vedic": 111,
        "horoscope/chartimage": 212,
        "prediction/dailysun": 71,
        "matching/ashtakoot": 111,
        "matching/papasamya": 111
      },
      "day14": {
        "total": 526,
        "horoscope/vedic": 12,
        "horoscope/chartimage": 212,
        "prediction/dailysun": 71,
        "matching/ashtakoot": 56,
        "matching/papasamya": 59
      },
      "day15": {
        "total": 476,
        "horoscope/vedic": 33,
        "horoscope/chartimage": 12,
        "prediction/dailysun": 71,
        "matching/ashtakoot": 555,
        "matching/papasamya": 12
      },
      "day16": {
        "total": 526,
        "horoscope/vedic": 111,
        "horoscope/chartimage": 212,
        "prediction/dailysun": 71,
        "matching/ashtakoot": 111,
        "matching/papasamya": 111
      },
      "day17": {
        "total": 526,
        "horoscope/vedic": 12,
        "horoscope/chartimage": 212,
        "prediction/dailysun": 71,
        "matching/ashtakoot": 56,
        "matching/papasamya": 59
      },
      "day18": {
        "total": 526,
        "horoscope/vedic": 111,
        "horoscope/chartimage": 212,
        "prediction/dailysun": 71,
        "matching/ashtakoot": 111,
        "matching/papasamya": 111
      },
      "day19": {
        "total": 526,
        "horoscope/vedic": 12,
        "horoscope/chartimage": 212,
        "prediction/dailysun": 71,
        "matching/ashtakoot": 56,
        "matching/papasamya": 59
      },
      "day20": {
        "total": 586,
        "horoscope/vedic": 33,
        "horoscope/chartimage": 12,
        "prediction/dailysun": 71,
        "matching/ashtakoot": 555,
        "matching/papasamya": 12
      },
      "day21": {
        "total": 526,
        "horoscope/vedic": 111,
        "horoscope/chartimage": 212,
        "prediction/dailysun": 71,
        "matching/ashtakoot": 111,
        "matching/papasamya": 111
      },
      "day22": {
        "total": 526,
        "horoscope/vedic": 12,
        "horoscope/chartimage": 212,
        "prediction/dailysun": 71,
        "matching/ashtakoot": 56,
        "matching/papasamya": 59
      },
      "day23": {
        "total": 643,
        "horoscope/vedic": 33,
        "horoscope/chartimage": 12,
        "prediction/dailysun": 71,
        "matching/ashtakoot": 555,
        "matching/papasamya": 12
      }
      ,
      "day24": {
        "total": 526,
        "horoscope/vedic": 111,
        "horoscope/chartimage": 212,
        "prediction/dailysun": 71,
        "matching/ashtakoot": 111,
        "matching/papasamya": 111
      },
      "day25": {
        "total": 526,
        "horoscope/vedic": 12,
        "horoscope/chartimage": 212,
        "prediction/dailysun": 71,
        "matching/ashtakoot": 56,
        "matching/papasamya": 59
      },
      "day26": {
        "total": 643,
        "horoscope/vedic": 33,
        "horoscope/chartimage": 12,
        "prediction/dailysun": 71,
        "matching/ashtakoot": 555,
        "matching/papasamya": 12
      }
      ,
      "day27": {
        "total": 526,
        "horoscope/vedic": 111,
        "horoscope/chartimage": 212,
        "prediction/dailysun": 71,
        "matching/ashtakoot": 111,
        "matching/papasamya": 111
      },
      "day28": {
        "total": 526,
        "horoscope/vedic": 12,
        "horoscope/chartimage": 212,
        "prediction/dailysun": 71,
        "matching/ashtakoot": 56,
        "matching/papasamya": 59
      },
      "day29": {
        "total": 643,
        "horoscope/vedic": 33,
        "horoscope/chartimage": 12,
        "prediction/dailysun": 71,
        "matching/ashtakoot": 555,
        "matching/papasamya": 12
      },
      
      "day30": {
        "total": 526,
        "horoscope/vedic": 111,
        "horoscope/chartimage": 212,
        "prediction/dailysun": 71,
        "matching/ashtakoot": 111,
        "matching/papasamya": 111
      },
      "day31": {
        "total": 526,
        "horoscope/vedic": 12,
        "horoscope/chartimage": 212,
        "prediction/dailysun": 71,
        "matching/ashtakoot": 56,
        "matching/papasamya": 59
      }
    }
  }
}
